espapp/__init__.py
espapp/daily.py
espapp/esp.py
espapp/data/data.txt
espapp/data/data2.txt
espapp/data/data3.txt
espapp/data/data4.txt
espapp/data/ethtoolpyth.py
espapp/data/log
espapp/data/main_ips.json
espapp/data/main_macs.json
espapp/data/main_names.json
espapp/data/output.txt
espapp/data/output2.txt
espapp/data/temp
espapp_pkg-0.6.0.1.dist-info/LICENSE
espapp_pkg-0.6.0.1.dist-info/METADATA
espapp_pkg-0.6.0.1.dist-info/WHEEL
espapp_pkg-0.6.0.1.dist-info/entry_points.txt
espapp_pkg-0.6.0.1.dist-info/top_level.txt
espapp_pkg-0.6.0.1.dist-info/RECORD
