Metadata-Version: 2.1
Name: espapp-pkg
Version: 0.6.0.1
Summary: ESP applicaion
Home-page: https://github.com/emb-karan/espapp-pkg
Author: Karan
Author-email: karan.rathore@viriminfotech.com
License: Virim
Platform: any
Requires-Python: !=2.7,!=3.0.*,!=3.1.*,!=3.2.*,!=3.3.*
Requires-Dist: uuid
Requires-Dist: python-crontab
Requires-Dist: requests
